<network nodes="12" radio="12">
    <grid>0.1m</grid>
    <tolerance quality="2">1E-4</tolerance>
    <xi:include href="channel.xml"/>
    <nodes>
	<defaults>
	<xi:include href="tag.xml"/>
	</defaults>
	<node number="0" type="peg">
	    <location>10.0 10.0</location>
	    <preinit tag="HID" type="lword">0xBACA0001</preinit>
	</node>
	<node number="1" type="peg" start="on">
	    <location>90.0 10.0</location>
	    <preinit tag="HID" type="lword">0xBACA0002</preinit>
	</node>
        <node number="2" type="peg" start="on">
            <location>170.0 10.0</location>
            <preinit tag="HID" type="lword">0xBACA0003</preinit>
        </node>
        <node number="3" type="peg" start="on">
            <location>250.0 10.0</location>
            <preinit tag="HID" type="lword">0xBACA0067</preinit>
        </node>

	<node number="4" type="peg" start="on">
	    <location>330.0 10.0</location>
	    <preinit tag="HID" type="lword">0xBACA0068</preinit>
	</node>
        <node number="5" type="col" start="on">
            <location>380.0 10.0</location>
            <preinit tag="HID" type="lword">0xBACA03ed</preinit>
        </node>
        <node number="6" type="col" start="on">
            <location>390.0 20.0</location>
            <preinit tag="HID" type="lword">0xBACA03ee</preinit>
        </node>

       <node number="7" type="col" start="on">
            <location>400.0 30.0</location>
            <preinit tag="HID" type="lword">0xBACA03ef</preinit>
        </node>

	<node number="8" type="col" start="on">
	    <location>230.0 100.0</location>
	    <preinit tag="HID" type="lword">0xBACA03f0</preinit>
	</node>
        <node number="9" type="col" start="on">
            <location>250.0 100.0</location>
            <preinit tag="HID" type="lword">0xBACA03f1</preinit>
        </node>
        <node number="10" type="col" start="on">
            <location>200.0 60.0</location>
            <preinit tag="HID" type="lword">0xBACA03f2</preinit>
        </node>
        <node number="11" type="col" start="on">
            <location>230.0 60.0</location>
            <preinit tag="HID" type="lword">0xBACA03f3</preinit>
        </node>
    </nodes>
</network>
